src/__init__.py
src/download.py
download_models-0.0.1.dist-info/METADATA
download_models-0.0.1.dist-info/WHEEL
download_models-0.0.1.dist-info/entry_points.txt
download_models-0.0.1.dist-info/top_level.txt
download_models-0.0.1.dist-info/RECORD
