Metadata-Version: 2.1
Name: download-models
Version: 0.0.1
Summary: Download models from hugging face
Author: Tangesion
Author-email: tangesion@163.com
Classifier: Programming Language :: Python :: 3
Classifier: License :: OSI Approved :: Apache Software License
Classifier: Operating System :: OS Independent
Requires-Dist: huggingface-hub ==0.20.2
Requires-Dist: Requests ==2.31.0
Requires-Dist: tqdm ==4.66.1
